CompartmentsPlus/Compartments+.lnk
CompartmentsPlus/CompartmentsPlusWeb.py
CompartmentsPlus/__init__.py
CompartmentsPlus/compartmentModel.py
CompartmentsPlus/serverSpinup.bat
tests/__init__.py
tests/test_compartmentModel.py
compartmentsPlus-0.1.4.dist-info/METADATA
compartmentsPlus-0.1.4.dist-info/WHEEL
compartmentsPlus-0.1.4.dist-info/top_level.txt
compartmentsPlus-0.1.4.dist-info/RECORD
