Metadata-Version: 2.1
Name: compartmentsPlus
Version: 0.1.4
Summary: Unified API for compartmental modeling
Author: ThreeStrings
Author-email: <zack@ouhermans.com>
Keywords: python,compartment,modeling,epidemiology,networks
Classifier: Development Status :: 5 - Production/Stable
Classifier: Intended Audience :: Science/Research
Classifier: Programming Language :: Python :: 3
Classifier: Operating System :: Unix
Classifier: Operating System :: MacOS :: MacOS X
Classifier: Operating System :: Microsoft :: Windows
Requires-Dist: streamlit
Requires-Dist: openpyxl
Requires-Dist: pandas
Requires-Dist: matplotlib
